aiowrpr/__init__.py
aiowrpr/adaptor.py
aiowrpr/generators.py
aiowrpr/routes.py
aiowrpr-0.0.1a7.dist-info/LICENSE
aiowrpr-0.0.1a7.dist-info/METADATA
aiowrpr-0.0.1a7.dist-info/WHEEL
aiowrpr-0.0.1a7.dist-info/entry_points.txt
aiowrpr-0.0.1a7.dist-info/top_level.txt
aiowrpr-0.0.1a7.dist-info/RECORD
